area55-0.0.1.dist-info/licenses/LICENCE
mylib55/__init__.py
mylib55/area55.py
area55-0.0.1.dist-info/METADATA
area55-0.0.1.dist-info/WHEEL
area55-0.0.1.dist-info/top_level.txt
area55-0.0.1.dist-info/RECORD
